README.rst
setup.py
ellis/__init__.py
ellis/__main__.py
ellis/action.py
ellis/ellis.py
ellis/exceptions.py
ellis/filter.py
ellis/main.py
ellis/matches.py
ellis/rule.py
ellis/search_matches.py
ellis.egg-info/PKG-INFO
ellis.egg-info/SOURCES.txt
ellis.egg-info/dependency_links.txt
ellis.egg-info/entry_points.txt
ellis.egg-info/requires.txt
ellis.egg-info/top_level.txt
ellis_actions/__init__.py
ellis_actions/dummy.py
ellis_actions/ipset.py
ellis_actions/mail-working.py
ellis_actions/mail.py
ellis_actions/nftables.py
ellis_actions/shell_commander.py